.coveragerc
.pre-commit-config.yaml
README.md
pyproject.toml
structlog_sentry/__init__.py
structlog_sentry/py.typed
tox.ini
structlog_sentry-2.2.0.dist-info/LICENSE
structlog_sentry-2.2.0.dist-info/METADATA
structlog_sentry-2.2.0.dist-info/WHEEL
structlog_sentry-2.2.0.dist-info/RECORD
