Metadata-Version: 2.1
Name: structlog-sentry
Version: 2.2.0
Summary: Sentry integration for structlog
Home-page: https://github.com/kiwicom/structlog-sentry
License: MIT
Author: Kiwi.com platform
Author-email: platform@kiwi.com
Requires-Python: >=3.7,<4.0
Classifier: Development Status :: 5 - Production/Stable
Classifier: Environment :: Web Environment
Classifier: Intended Audience :: Developers
Classifier: License :: OSI Approved :: MIT License
Classifier: Programming Language :: Python
Classifier: Programming Language :: Python :: 3
Classifier: Programming Language :: Python :: 3.7
Classifier: Programming Language :: Python :: 3.8
Classifier: Programming Language :: Python :: 3.9
Classifier: Programming Language :: Python :: 3.10
Classifier: Programming Language :: Python :: 3.11
Classifier: Programming Language :: Python :: 3.12
Classifier: Programming Language :: Python :: 3.13
Classifier: Topic :: Software Development :: Libraries :: Python Modules
Requires-Dist: sentry-sdk (>=2.0,<3.0)
Requires-Dist: structlog
Project-URL: Repository, https://github.com/kiwicom/structlog-sentry
